arcosparse/__init__.py
arcosparse/chunk_selector.py
arcosparse/downloader.py
arcosparse/environment_variables.py
arcosparse/logger.py
arcosparse/models.py
arcosparse/sessions.py
arcosparse/subsetter.py
arcosparse/utils.py
arcosparse-0.4.0.dist-info/LICENSE
arcosparse-0.4.0.dist-info/METADATA
arcosparse-0.4.0.dist-info/WHEEL
arcosparse-0.4.0.dist-info/RECORD
