Metadata-Version: 2.3
Name: arcosparse
Version: 0.4.0
Summary: Helper to download and subset sparse data that has been Arcoified and are available through STAC and sqlite formated data
License: AGPL-3.0-only
Author: renaudjester
Author-email: renaud.jester@lobelia.earth
Requires-Python: >=3.9
Classifier: License :: OSI Approved :: GNU Affero General Public License v3
Classifier: Programming Language :: Python :: 3
Classifier: Programming Language :: Python :: 3.9
Classifier: Programming Language :: Python :: 3.10
Classifier: Programming Language :: Python :: 3.11
Classifier: Programming Language :: Python :: 3.12
Classifier: Programming Language :: Python :: 3.13
Requires-Dist: pandas (>=2,<3)
Requires-Dist: pyarrow (>=17.0.0)
Requires-Dist: pystac (>=1.8.3,<2.0.0)
Requires-Dist: requests (>=2.27.1,<3.0.0)
Requires-Dist: tqdm (>=4.65,<5.0)
